{
    "fileName":"Jane Austen___Persuasion.txt",
    "numPars":216,
    "characters":[
        {
            "mainName":"anne",
            "mentions":[
                "Anne",
                "she",
                "her",
                "she",
                "her",
                "her",
                "her",
                "her",
                "She",
                "her",
                "her",
                "she",
                "her",
                "Her",
                "her",
                "her",
                "She",
                "her",
                "her",
                "her",
                "her",
                "her",
                "she"
            ],
            "aliases":[
                "she",
                "anne",
                "her"
            ],
            "agent":[
                {
                    "[214, 0, 2]":"satisfy"
                },
                {
                    "[214, 1, 55]":"feel"
                },
                {
                    "[214, 3, 149]":"have"
                },
                {
                    "[214, 6, 224]":"be"
                },
                {
                    "[214, 8, 284]":"be"
                },
                {
                    "[214, 9, 349]":"requite"
                }
            ],
            "patient":[
                {
                    "[214, 2, 74]":"give"
                },
                {
                    "[214, 6, 224]":"be"
                },
                {
                    "[214, 7, 261]":"be"
                },
                {
                    "[214, 9, 349]":"requite"
                }
            ]
        },
        {
            "mainName":"mr elliot",
            "mentions":[
                "Mr Elliot",
                "himself",
                "him",
                "his",
                "Mr Elliot",
                "his",
                "his",
                "he",
                "his",
                "his",
                "He",
                "his",
                "he",
                "he",
                "himself",
                "his"
            ],
            "aliases":[
                "mr elliot",
                "his",
                "himself",
                "he",
                "him"
            ],
            "agent":[
                {
                    "[213, 13, 530]":"have"
                },
                {
                    "[213, 16, 621]":"do"
                },
                {
                    "[213, 17, 635]":"quit"
                }
            ],
            "patient":[
                {
                    "[213, 13, 530]":"have"
                },
                {
                    "[213, 17, 635]":"quit"
                }
            ]
        },
        {
            "mainName":"lady russell",
            "mentions":[
                "Lady Russell",
                "Lady Russell",
                "her"
            ],
            "aliases":[
                "lady russell",
                "her"
            ],
            "agent":[
                {
                    "[214, 5, 197]":"value"
                }
            ],
            "patient":[]
        },
        {
            "mainName":"captain wentworth",
            "mentions":[
                "Captain Wentworth",
                "Captain Wentworth"
            ],
            "aliases":[
                "captain wentworth"
            ],
            "agent":[
                {
                    "[213, 9, 347]":"be"
                }
            ],
            "patient":[
                {
                    "[213, 11, 463]":"have"
                }
            ]
        },
        {
            "mainName":"he",
            "mentions":[
                "he",
                "myself",
                "myself",
                "myself",
                "me",
                "me"
            ],
            "aliases":[
                "he",
                "me",
                "myself"
            ],
            "agent":[
                {
                    "[206, 0, 8]":"end"
                }
            ],
            "patient":[
                {
                    "[206, 1, 36]":"do"
                }
            ]
        }
    ]
}